aldine/__dynamic_blocks_placeholder.py
aldine/__init__.py
aldine/apps.py
aldine/auxiliaries.py
aldine/blocks.py
aldine/cells.py
aldine/images.py
aldine/render.py
aldine/static/aldine/css/aldine.css
aldine/templatetags/__init__.py
aldine/templatetags/aldine_tags.py
aldine-4.1.1.dist-info/AUTHORS.txt
aldine-4.1.1.dist-info/LICENSE.txt
aldine-4.1.1.dist-info/METADATA
aldine-4.1.1.dist-info/WHEEL
aldine-4.1.1.dist-info/top_level.txt
aldine-4.1.1.dist-info/RECORD
