Metadata-Version: 2.1
Name: aldine
Version: 4.1.1
Summary: A Wagtail app for facilitating responsive rendering.
Home-page: https://github.com/high-dimensional/aldine
Author: High Dimensional Neurology Group, UCL
Author-email: pypi@highdimensional.net
License: BSD-3-Clause
Platform: any
Classifier: Framework :: Django
Classifier: Framework :: Wagtail
Classifier: Programming Language :: Python :: 3
Classifier: Programming Language :: Python :: 3.8
Classifier: License :: OSI Approved :: BSD License
Classifier: Operating System :: OS Independent
Requires-Python: ~=3.8
License-File: LICENSE.txt
License-File: AUTHORS.txt
Requires-Dist: Django (<4.2,>=4.1)
Requires-Dist: wagtail (<4.2,>=4.1)
Requires-Dist: steadfast (<1.1,>=1.0)
Requires-Dist: csskit (<1.1,>=1.0)
Requires-Dist: wagtail-content-admin (<4.2,>=4.1)
